<?xml version="1.0" encoding="UTF-8"?>
<listWit>
    <witness xml:id="N">Naples, Biblioteca Nazionale di Napoli V A 8, XV </witness>
    <witness xml:id="G">Florence, Biblioteca Medicea Laurenziana [Catalog Number] pl. 90, 12 inf ,
        XV </witness>
    <witness xml:id="P">Paris, Bibliothèque Nationale 8049, XII </witness>
    <witness xml:id="A">Florence, Biblioteca Riccardiana 636, XV </witness>
    <witness xml:id="H">London, British Library 2578, </witness>
    <listWit xml:id="V">
        <witness xml:id="α">Milan, Biblioteca Ambrosiana O.74 sup., XV </witness>
        <witness xml:id="β">Milan, Biblioteca Ambrosiana I 26 sup., XV </witness>
        <witness xml:id="δ">Wrocław, 1.4.11, XV </witness>
        <witness xml:id="γ">Vatican City, Vatican Library 3152, XV </witness>
        <witness xml:id="λ">Florence, Biblioteca Medicea Laurenziana [Catalog Number] Aed. 203, XV </witness>
        <witness xml:id="ε">Vatican City, Vatican Library Urbinas 353, XV </witness>
        <witness xml:id="μ">Vatican City, Vatican Library 2110, XV </witness>
        <witness xml:id="κ">Florence, Biblioteca Riccardiana 724, XVI </witness>
        <witness xml:id="φ">Vatican City, Vatican Library Ottobonianus 1466, XV </witness>
        <witness xml:id="χ">Vatican City, Vatican Library Reginensis 1759, XV </witness>
        <witness xml:id="ν">Vatican City, Vatican Library Palatinus 1652, XV </witness>
        <witness xml:id="π">Vatican City, Vatican Library Palatinus 1652, XV </witness>
        <witness xml:id="η">Wrocław, 1.4.10, XV </witness>
        <witness xml:id="ρ">Florence, Biblioteca Riccardiana 636, XV </witness>
        <witness xml:id="θ">Gotha, Forschungsbibliothek 55, XIV </witness>
        <witness xml:id="ζ">Florence, Biblioteca Riccardiana 974, XV </witness>
    </listWit>
    <witness xml:id="ω">codicum omnium consensus</witness>
    <witness xml:id="Exc. Par.">[Library], </witness>
    <witness xml:id="Exc. Bon.">[Library], </witness>
</listWit>
